{
  "last_watchdog": "2026-07-13 17:02:34",
  "runs": {
    "Portfolio Bot": {
      "last_run": "2026-07-13 06:00:22",
      "success": true,
      "duration": 20,
      "last_output": "ng investment in high-performing ones like VAML to capitalize on their growth momentum.\n\u2501\u2501\u2501\u2501\u2501\u2501\u2501\u2501\u2501\u2501\u2501\u2501\u2501\u2501\u2501\u2501\u2501\u2501\u2501\u2501\u2501\u2501\u2501\u2501\u2501\u2501\u2501\u2501\u2501\u2501\n2026-07-13 06:00:21,619  INFO  WhatsApp sent to +919818187001\n2026-07-13 06:00:22,021  INFO  WhatsApp sent to +919810238955\n2026-07-13 06:00:22,024  INFO  === Portfolio Bot Done ===",
      "runs_today": 1
    },
    "Utility Bill Bot": {
      "last_run": "2026-07-13 10:00:22",
      "success": true,
      "duration": 13,
      "last_output": "for new PDFs...\n\ud83d\udced [bses] no new emails since last send (UID 162003)\n\n\ud83d\udcb3 [icici] ICICI Amazon Pay Credit Card \u2014 checking for new PDFs...\n\ud83d\udced [icici] no new emails since last send (UID 161873)\n\n\ud83d\udcb3 [hdfc] HDFC Credit Card \u2014 checking for new PDFs...\n\ud83d\udced [hdfc] no new emails since last send (UID 161641)\n\u2705 Done",
      "runs_today": 1
    },
    "Chia AI Watcher": {
      "last_run": "2026-07-13 19:13:14",
      "success": true,
      "duration": 22,
      "last_output": "\u2705 Chia AI (ok): Multiple plot quality lookups exceeded the recommended time threshold.\n  \u2022 Looking up qualities on multiple plots took over 33 seconds, exceeding the 20-second recommendation.",
      "runs_today": 10
    },
    "Chia Health Monitor": {
      "last_run": "2026-07-13 08:00:19",
      "success": true,
      "duration": 4,
      "last_output": "*Chia Health \u2014 Daily*\n\u2705 Status: Farming | 13476 plots\n\ud83d\udea8 Last win: 67h ago (expected 17h)\n\u2705 Prover errors: 4 (2 unique plots) [known giga37 bug]\n\u2705 Block validation: normal\n\n\ud83d\udea8 *ALERTS*: No win in 67h (>3\u00d7 expected)",
      "runs_today": 1
    },
    "Crypto Portfolio Bot": {
      "last_run": "2026-07-13 09:00:37",
      "success": true,
      "duration": 10,
      "last_output": "Base L2 wallet 0x0e5223\u2026: Empty Hive response\n  \u26a0 ETH wallet 0x0e5223\u2026: Empty Hive response\n  \u26a0 BSC wallet 0xB38F0e\u2026: Empty Hive response\n  \u26a0 Base L2 wallet 0xB38F0e\u2026: Empty Hive response\n  \u26a0 ETH wallet 0xB38F0e\u2026: Empty Hive response\n\u274c All holdings lookups failed \u2014 reporting portfolio as unavailable",
      "runs_today": 1
    }
  },
  "last_watchdog_alert_sig": ""
}